modb/__init__.py
modb/constant.py
modb/error.py
modb/format.py
modb/formatcore.py
modb/high.py
modb/log.py
modb/low.py
modb/utils.py
modb_py-0.2.dist-info/LICENSE
modb_py-0.2.dist-info/METADATA
modb_py-0.2.dist-info/WHEEL
modb_py-0.2.dist-info/top_level.txt
modb_py-0.2.dist-info/RECORD
