Metadata-Version: 2.1
Name: modb-py
Version: 0.2
Summary: modb, on-disk-database, the replacement for open. no third party dependency, using btree internally.
Home-page: https://github.com/Darcy-C/modb
Author: Darcy-C
License: UNKNOWN
Platform: UNKNOWN
Classifier: Programming Language :: Python :: 3
Classifier: License :: OSI Approved :: MIT License
Classifier: Operating System :: OS Independent
Requires-Python: >=3.6
License-File: LICENSE
